.gitignore
LICENSE
MANIFEST.in
README.md
setup.py
dsfinterp/__init__.py
dsfinterp/channel.py
dsfinterp/channelgroup.py
dsfinterp/dsf.py
dsfinterp/dsfgroup.py
dsfinterp/dsfload.py
dsfinterp/dsfsave.py
dsfinterp/interpolator.py
dsfinterp/logger.py
dsfinterp.egg-info/PKG-INFO
dsfinterp.egg-info/SOURCES.txt
dsfinterp.egg-info/dependency_links.txt
dsfinterp.egg-info/top_level.txt
dsfinterp/test/__init__.py
dsfinterp/test/channel_test.py
dsfinterp/test/channelgroup_test.py
dsfinterp/test/dsf_test.py
dsfinterp/test/dsfgroup_test.py
dsfinterp/test/dsfload_test.py
dsfinterp/test/dsfsave_test.py
dsfinterp/test/interpolator_test.py
dsfinterp/test/data/exp100K.nxs
dsfinterp/test/data/exp150K.nxs
dsfinterp/test/data/exp175K.nxs
dsfinterp/test/data/exp200K.nxs
dsfinterp/test/data/exp225K.nxs
dsfinterp/test/data/exp250K.nxs
dsfinterp/test/data/exp300K.nxs
dsfinterp/test/data/exp350K.nxs
dsfinterp/test/data/sim200K.nxs