Metadata-Version: 1.1
Name: dsfinterp
Version: 0.1
Summary: Cubic Spline Interpolation of Dynamics Structure Factors
Home-page: https://github.com/camm-sns/dsfinterp
Author: Jose Borreguero
Author-email: jose@borreguero.com
License: UNKNOWN
Download-URL: http://pypi.python.org/pypi/dsfinterp
Keywords: AMBER,mdend,energy,molecular dynamics
Platform: UNKNOWN
Classifier: Programming Language :: Python
Classifier: Programming Language :: Python :: 2.7
Classifier: Development Status :: 4 - Beta
Classifier: Intended Audience :: Science/Research
Classifier: License :: OSI Approved :: MIT License
Classifier: Operating System :: OS Independent
Classifier: Topic :: Scientific/Engineering :: Physics
